{
  "color": "blue",
  "title": "DCS Server Overview",
  "elements": [
    {
      "class": "plugins.community.report.Top10Servers"
    },
    {
      "type": "Ruler",
      "params": {
        "ruler_length": 20
      }
    },
    {
      "type": "Graph",
      "params": {
        "width": 15,
        "height": 5,
        "rows": 1,
        "cols": 2,
        "elements":
         [
            {
              "class": "plugins.community.report.AllServers",
              "params": { "row": 0, "col": 0, "colspan": 2 }
            }
         ]
      }
    }
  ]
}